README.md
setup.py
shellium/__init__.py
shellium/exceptions.py
shellium/extensions.py
shellium/options.py
shellium/webdriver.py
shellium.egg-info/PKG-INFO
shellium.egg-info/SOURCES.txt
shellium.egg-info/dependency_links.txt
shellium.egg-info/requires.txt
shellium.egg-info/top_level.txt