Metadata-Version: 2.1
Name: shellium
Version: 18
Summary: The package provides a wrapper for working with chrome driver.
Home-page: https://github.com/GooseG4G/shellium
Author: GooseG4G
Author-email: danilnegusev@inbox.ru
Requires-Python: >=3.10.6
Requires-Dist: psutil
Requires-Dist: selenium==4.22.0
Requires-Dist: undetected_chromedriver==3.5.5
